.travis.yml
LICENSE.txt
MANIFEST.in
README.md
requirements.txt
setup.cfg
setup.py
vanitynumber/__init__.py
vanitynumber/data_cleaning.py
vanitynumber/defaults.yml
vanitynumber/dictionary.txt
vanitynumber/helper.py
vanitynumber/t9_graph_node.py
vanitynumber/version.py
vanitynumber/wordify.py
vanitynumber.egg-info/PKG-INFO
vanitynumber.egg-info/SOURCES.txt
vanitynumber.egg-info/dependency_links.txt
vanitynumber.egg-info/not-zip-safe
vanitynumber.egg-info/requires.txt
vanitynumber.egg-info/top_level.txt
vanitynumber/tests/__init__.py
vanitynumber/tests/test_helper.py
vanitynumber/tests/test_wordify.py