Metadata-Version: 2.1
Name: vanitynumber
Version: 0.4
Summary: Vanity Number Wordification
Home-page: https://github.com/sreenivasanac/vanitynumber
Author: Sreenivasan AC
Author-email: sreenivasan.nitt@gmail.com
License: EULA
Download-URL: https://github.com/sreenivasanac/vanitynumber/archive/v_0.4.tar.gz
Keywords: Vanity Number,Toll-free number,Wordification,Marketing,Phone Number
Platform: UNKNOWN
Classifier: Development Status :: 3 - Alpha
Classifier: Intended Audience :: Developers
Classifier: Topic :: Software Development :: Build Tools
Classifier: License :: OSI Approved :: MIT License
Classifier: Programming Language :: Python :: 3.7
